{
  "project_info": {
    "project_number": "1012561643795",
    "project_id": "fir-para-flutter-bd544",
    "storage_bucket": "fir-para-flutter-bd544.appspot.com"
  },
  "client": [
    {
      "client_info": {
        "mobilesdk_app_id": "1:1012561643795:android:5197cb9674355eb61132e6",
        "android_client_info": {
          "package_name": "com.example.gtk_flutter"
        }
      },
      "oauth_client": [
        {
          "client_id": "1012561643795-8cctsdcepldes2rjdj5tg7t3cjefmp3b.apps.googleusercontent.com",
          "client_type": 3
        }
      ],
      "api_key": [
        {
          "current_key": "AIzaSyBqcW1kNQq7-IbceF4ou71F5U_VTtMmrls"
        }
      ],
      "services": {
        "appinvite_service": {
          "other_platform_oauth_client": [
            {
              "client_id": "1012561643795-8cctsdcepldes2rjdj5tg7t3cjefmp3b.apps.googleusercontent.com",
              "client_type": 3
            }
          ]
        }
      }
    }
  ],
  "configuration_version": "1"
}